eagerx_ode/__init__.py
eagerx_ode/engine.py
eagerx_ode/engine_nodes.py
eagerx_ode/engine_states.py
eagerx_ode-0.1.26.dist-info/LICENSE
eagerx_ode-0.1.26.dist-info/WHEEL
eagerx_ode-0.1.26.dist-info/METADATA
eagerx_ode-0.1.26.dist-info/RECORD
