Metadata-Version: 2.1
Name: eagerx-ode
Version: 0.1.26
Summary: Engine (with corresponding nodes) that uses arbitrary ODEs to simulate objects in EAGERx.
Home-page: https://github.com/eager-dev/eagerx_ode
License: Apache2.0
Author: Jelle Luijkx
Author-email: j.d.luijkx@tudelft.nl
Requires-Python: >=3.6.2,<4.0.0
Classifier: License :: Other/Proprietary License
Classifier: Programming Language :: Python :: 3
Classifier: Programming Language :: Python :: 3.7
Classifier: Programming Language :: Python :: 3.8
Classifier: Programming Language :: Python :: 3.9
Classifier: Programming Language :: Python :: 3.10
Requires-Dist: eagerx (>=0.1.31,<0.2.0)
Requires-Dist: scipy (>=1.5.4,<2.0.0)
Project-URL: Documentation, https://eagerx.readthedocs.io/en/master/
Project-URL: Repository, https://github.com/eager-dev/eagerx_ode
